azureml_infra_tools/__init__.py
azureml_infra_tools/cluster.py
azureml_infra_tools/credential.py
azureml_infra_tools/data.py
azureml_infra_tools/environment.py
azureml_infra_tools-0.1.1.dist-info/LICENSE
azureml_infra_tools-0.1.1.dist-info/METADATA
azureml_infra_tools-0.1.1.dist-info/WHEEL
azureml_infra_tools-0.1.1.dist-info/RECORD
