Metadata-Version: 2.1
Name: azureml-infra-tools
Version: 0.1.1
Summary: azureml-infra-tools is a Python package providing high-level APIs for Azure Machine Learning. It simplifies setup of Azure ML infrastructures, manages datasets, and streamlines authentication. Designed for AI researchers, data scientists, and ML engineers, it boosts productivity and accelerates Azure ML projects.
License: MIT
Author: Henrique Malta
Author-email: vlezyitalia@gmail.com
Requires-Python: >=3.10,<4.0
Classifier: License :: OSI Approved :: MIT License
Classifier: Programming Language :: Python :: 3
Classifier: Programming Language :: Python :: 3.10
Classifier: Programming Language :: Python :: 3.11
Requires-Dist: azure-ai-ml (>=1.8.0,<2.0.0)
Requires-Dist: azure-identity (>=1.13.0,<2.0.0)
Requires-Dist: python-dotenv (>=1.0.0,<2.0.0)
Requires-Dist: urllib3 (==1.26.9)
